SpanishWF/__init__.py
SpanishWF/calc.py
SpanishWF/consts.py
SpanishWF/parameters.py
SpanishWF/specificpredictions.py
SpanishWF/swfunctions.py
SpanishWF/urls.py
spanishwf-0.0.4.dist-info/METADATA
spanishwf-0.0.4.dist-info/WHEEL
spanishwf-0.0.4.dist-info/licenses/LICENSE
spanishwf-0.0.4.dist-info/RECORD
