Metadata-Version: 2.1
Name: SpanishWF
Version: 0.0.4
Summary: Prevision Meteorologica Aemet
Project-URL: Homepage, https://github.com/Miguel-bc/SpanishWF.git
Project-URL: Bug Tracker, https://github.com/Miguel-bc/SpanishWF.git/issues
Author-email: Miguel Blaya <miguel.blaya@gmail.com>
License: MIT License
License-File: LICENSE
Classifier: License :: OSI Approved :: MIT License
Classifier: Operating System :: OS Independent
Classifier: Programming Language :: Python :: 3
Requires-Python: >=3.9
